{
    "name": "Global Information",
    "numberOfRequests": {
        "total": 6,
        "ok": 5,
        "ko": 1
    },
    "minResponseTime": {
        "total": 11,
        "ok": 166,
        "ko": 11
    },
    "maxResponseTime": {
        "total": 2779,
        "ok": 2779,
        "ko": 11
    },
    "meanResponseTime": {
        "total": 801,
        "ok": 958,
        "ko": 11
    },
    "standardDeviation": {
        "total": 924,
        "ok": 935,
        "ko": 0
    },
    "percentiles1": {
        "total": 524,
        "ok": 632,
        "ko": 11
    },
    "percentiles2": {
        "total": 758,
        "ok": 800,
        "ko": 11
    },
    "percentiles3": {
        "total": 2284,
        "ok": 2383,
        "ko": 11
    },
    "percentiles4": {
        "total": 2680,
        "ok": 2700,
        "ko": 11
    },
    "group1": {
    "name": "t < 800 ms",
    "count": 3,
    "percentage": 50
},
    "group2": {
    "name": "800 ms < t < 1200 ms",
    "count": 1,
    "percentage": 17
},
    "group3": {
    "name": "t > 1200 ms",
    "count": 1,
    "percentage": 17
},
    "group4": {
    "name": "failed",
    "count": 1,
    "percentage": 17
},
    "meanNumberOfRequestsPerSecond": {
        "total": 0.75,
        "ok": 0.625,
        "ko": 0.125
    }
}